{
  "resourceType": "ValueSet",
  "id": "ACP-EuthanasiaStatement",
  "url": "https://api.iknl.nl/docs/pzp/stu3/ValueSet/ACP-EuthanasiaStatement",
  "version": "1.0.0-rc1",
  "name": "ACPEuthanasiaStatementVS",
  "title": "Euthanasia Statement",
  "status": "draft",
  "experimental": false,
  "publisher": "IKNL",
  "contact": [ {
    "name": "IKNL",
    "telecom": [ {
      "system": "email",
      "value": "info@iknl.nl",
      "use": "work"
    } ]
  } ],
  "description": "ValueSet for Position Regarding Euthanasia, representing the the patient's position regarding euthanasia and information on the presence of a euthanasia statement.",
  "copyright": "Copyright and related rights waived via CC0, https://creativecommons.org/publicdomain/zero/1.0/. This does not apply to information from third parties, for example a medical terminology system. The implementer alone is responsible for identifying and obtaining any necessary licenses or authorizations to utilize third party IP in connection with the specification or otherwise.",
  "compose": {
    "include": [ {
      "system": "http://terminology.hl7.org/CodeSystem/v3-NullFlavor",
      "concept": [ {
        "code": "UNK",
        "display": "Nog onbekend",
        "designation": [ {
          "language": "nl-NL",
          "use": {
            "system": "http://snomed.info/sct",
            "code": "900000000000013009",
            "display": "Synonym"
          },
          "value": "Onbekend"
        } ]
      } ]
    }, {
      "system": "http://snomed.info/sct",
      "concept": [ {
        "code": "340181000146102",
        "display": "Heeft euthanasieverklaring"
      }, {
        "code": "340201000146103",
        "display": "Wenst geen euthanasie"
      }, {
        "code": "340191000146100",
        "display": "Geen euthanasieverklaring, zou wel verzoek kunnen doen in bepaalde situaties"
      } ]
    } ]
  }
}